MF_Helpers/Reports.py
MF_Helpers/Utils.py
MF_Helpers/__init__.py
MF_Helpers/tests/__init__.py
MF_Helpers/tests/test_reports.py
MF_Helpers-0.7.dist-info/METADATA
MF_Helpers-0.7.dist-info/RECORD
MF_Helpers-0.7.dist-info/WHEEL
MF_Helpers-0.7.dist-info/top_level.txt
