Metadata-Version: 2.1
Name: MF-Helpers
Version: 0.7
Summary: Modeling Factory Utilities
Home-page: https://vc-bds002.vimpelcom.global/model-factory/MF_Helpers
Author: Natalia Galanova
Author-email: NGalanova@nsk.beeline.ru
License: UNKNOWN
Platform: UNKNOWN
Requires-Dist: numpy
Requires-Dist: pandas
Requires-Dist: sklearn
Requires-Dist: datetime
